{
    "rates": {
        "165-162": [
            {
                "changer": 417,
                "rate": "625.3917",
                "rankrate": "625.3917",
                "reserve": "97675",
                "inmin": "2000",
                "inmax": "10000000",
                "marks": [
                    "manual"
                ],
                "extra": []
            },
            {
                "changer": 622,
                "rate": "621.9302",
                "rankrate": "621.9302",
                "reserve": "13661",
                "inmin": "1507.17",
                "inmax": "731935823.9",
                "marks": [
                    "manual"
                ],
                "extra": []
            }
        ]
    }
}