{
    "rates": {
        "194-180": [
            {
                "changer": 984,
                "rate": "23.30507604",
                "rankrate": "23.30507604",
                "reserve": "1000",
                "inmin": "1",
                "inmax": "9999999999",
                "marks": [
                    "manual"
                ],
                "extra": []
            },
            {
                "changer": 989,
                "rate": "21.17351227",
                "rankrate": "21.17351227",
                "reserve": "5003576.896",
                "inmin": "4651.2967",
                "inmax": "148841",
                "marks": [
                    "cardverify",
                    "manual",
                    "otherin"
                ],
                "extra": []
            }
        ]
    }
}