{
    "rates": {
        "202-240": [
            {
                "changer": 417,
                "rate": "0.007719951056",
                "rankrate": "0.007719951056",
                "reserve": "851292",
                "inmin": "5.40396744",
                "inmax": "72310",
                "marks": [
                    "manual",
                    "otherout"
                ],
                "extra": []
            },
            {
                "changer": 517,
                "rate": "0.007560590573",
                "rankrate": "0.007560590573",
                "reserve": "189612",
                "inmin": "24.66166467",
                "inmax": "3627.373052",
                "marks": [
                    "manual"
                ],
                "extra": []
            },
            {
                "changer": 607,
                "rate": "0.007218913554",
                "rankrate": "0.007218913554",
                "reserve": "1951811",
                "inmin": "7.2182",
                "inmax": "144489.1859",
                "marks": [
                    "manual"
                ],
                "extra": []
            },
            {
                "changer": 619,
                "rate": "0.006689121129",
                "rankrate": "0.006689121129",
                "reserve": "94290.87",
                "inmin": "8.027",
                "inmax": "703.0266",
                "marks": [
                    "floating"
                ],
                "extra": []
            },
            {
                "changer": 622,
                "rate": "0.007810779188",
                "rankrate": "0.007810779188",
                "reserve": "10883000",
                "inmin": "8.31379048",
                "inmax": "7228400",
                "marks": [
                    "manual",
                    "otherout"
                ],
                "extra": []
            },
            {
                "changer": 989,
                "rate": "0.00811148579",
                "rankrate": "0.00811148579",
                "reserve": "105033",
                "inmin": "18.5785",
                "inmax": "595",
                "marks": [
                    "manual",
                    "otherout"
                ],
                "extra": []
            },
            {
                "changer": 1073,
                "rate": "0.00768367833",
                "rankrate": "0.00768367833",
                "reserve": "2730452",
                "inmin": "7",
                "inmax": "1500",
                "marks": [
                    "manual"
                ],
                "extra": []
            },
            {
                "changer": 1170,
                "rate": "0.006715736458",
                "rankrate": "0.006715736458",
                "reserve": "2000000",
                "inmin": "14.4358471",
                "inmax": "721.7923548",
                "marks": [
                    "manual"
                ],
                "extra": []
            },
            {
                "changer": 1181,
                "rate": "0.00703558953",
                "rankrate": "0.00703558953",
                "reserve": "8255253.62",
                "inmin": "14.07117906",
                "inmax": "58080.57593",
                "marks": [
                    "manual"
                ],
                "extra": []
            },
            {
                "changer": 1248,
                "rate": "0.006934191683",
                "rankrate": "0.006934191683",
                "reserve": "2000000",
                "inmin": "14.4358471",
                "inmax": "144.358471",
                "marks": [
                    "manual"
                ],
                "extra": []
            }
        ]
    }
}