{
    "rates": {
        "23-55": [
            {
                "changer": 337,
                "rate": "1.006118205",
                "rankrate": "1.006118205",
                "reserve": "1371027.18",
                "inmin": "804.894563",
                "inmax": "84616.55326",
                "marks": [
                    "manual"
                ],
                "extra": []
            },
            {
                "changer": 362,
                "rate": "1.09478154",
                "rankrate": "1.099999999",
                "reserve": "19957.93",
                "inmin": "16",
                "inmax": "5000",
                "marks": [],
                "extra": {
                    "tofee": {
                        "value": "1.3",
                        "type": "absolute"
                    }
                }
            },
            {
                "changer": 531,
                "rate": "1.019344751",
                "rankrate": "1.019344751",
                "reserve": "1000000",
                "inmin": "606.9175",
                "inmax": "6069.175",
                "marks": [
                    "floating",
                    "manual"
                ],
                "extra": []
            },
            {
                "changer": 626,
                "rate": "1.012958987",
                "rankrate": "1.012958987",
                "reserve": "963135.9512",
                "inmin": "1012.958781",
                "inmax": "202591.7563",
                "marks": [
                    "manual"
                ],
                "extra": []
            },
            {
                "changer": 640,
                "rate": "1.013254606",
                "rankrate": "1.013254606",
                "reserve": "1922978.18",
                "inmin": "911.928942",
                "inmax": "126656.7976",
                "marks": [
                    "manual"
                ],
                "extra": []
            },
            {
                "changer": 688,
                "rate": "1.008006596",
                "rankrate": "1.008006596",
                "reserve": "457953",
                "inmin": "856.805606",
                "inmax": "151200.9895",
                "marks": [
                    "manual"
                ],
                "extra": []
            },
            {
                "changer": 716,
                "rate": "1.019453206",
                "rankrate": "1.019453206",
                "reserve": "66949.04592",
                "inmin": "1019.453206",
                "inmax": "68251.41951",
                "marks": [
                    "manual"
                ],
                "extra": []
            },
            {
                "changer": 730,
                "rate": "1.013406353",
                "rankrate": "1.013406353",
                "reserve": "1212442",
                "inmin": "1013.406353",
                "inmax": "20000",
                "marks": [
                    "manual"
                ],
                "extra": []
            },
            {
                "changer": 790,
                "rate": "1.01734885",
                "rankrate": "1.01734885",
                "reserve": "1938976",
                "inmin": "813.87908",
                "inmax": "166897.0962",
                "marks": [
                    "manual"
                ],
                "extra": []
            },
            {
                "changer": 816,
                "rate": "1.013060303",
                "rankrate": "1.013060303",
                "reserve": "947825",
                "inmin": "1045.478306",
                "inmax": "194507.5919",
                "marks": [
                    "manual"
                ],
                "extra": []
            },
            {
                "changer": 898,
                "rate": "1.006318483",
                "rankrate": "1.006318483",
                "reserve": "1116323.144",
                "inmin": "805.05494",
                "inmax": "150947.8012",
                "marks": [
                    "manual"
                ],
                "extra": []
            },
            {
                "changer": 921,
                "rate": "1.006319688",
                "rankrate": "1.006319688",
                "reserve": "1935847",
                "inmin": "720",
                "inmax": "53000",
                "marks": [
                    "manual"
                ],
                "extra": []
            },
            {
                "changer": 944,
                "rate": "1.0244587",
                "rankrate": "1.0244587",
                "reserve": "108966.24",
                "inmin": "409.7835",
                "inmax": "10244.587",
                "marks": [],
                "extra": []
            },
            {
                "changer": 950,
                "rate": "1.01314036",
                "rankrate": "1.01314036",
                "reserve": "1988890.428",
                "inmin": "759.8552697",
                "inmax": "162102.4575",
                "marks": [
                    "floating",
                    "manual"
                ],
                "extra": []
            },
            {
                "changer": 981,
                "rate": "1.02344",
                "rankrate": "1.02344",
                "reserve": "1544704.29",
                "inmin": "409.38",
                "inmax": "10234.4",
                "marks": [
                    "manual"
                ],
                "extra": []
            },
            {
                "changer": 1034,
                "rate": "1.019345",
                "rankrate": "1.019345",
                "reserve": "400766.65",
                "inmin": "407.738",
                "inmax": "9683.7775",
                "marks": [],
                "extra": []
            },
            {
                "changer": 1056,
                "rate": "1.013154843",
                "rankrate": "1.013154843",
                "reserve": "782102",
                "inmin": "1013.154801",
                "inmax": "15197.32203",
                "marks": [
                    "manual"
                ],
                "extra": []
            },
            {
                "changer": 1086,
                "rate": "1.023343",
                "rankrate": "1.023343",
                "reserve": "703784.28",
                "inmin": "409.3372",
                "inmax": "100000",
                "marks": [],
                "extra": []
            },
            {
                "changer": 1138,
                "rate": "1.005771115",
                "rankrate": "1.005771115",
                "reserve": "1000000",
                "inmin": "804.616892",
                "inmax": "1005771.115",
                "marks": [
                    "manual"
                ],
                "extra": []
            },
            {
                "changer": 1170,
                "rate": "1.035161325",
                "rankrate": "1.035161325",
                "reserve": "300300",
                "inmin": "700.7",
                "inmax": "20020",
                "marks": [
                    "manual"
                ],
                "extra": []
            },
            {
                "changer": 1181,
                "rate": "1.01",
                "rankrate": "1.01",
                "reserve": "365027.5065",
                "inmin": "707",
                "inmax": "368677.78",
                "marks": [
                    "manual"
                ],
                "extra": []
            },
            {
                "changer": 1256,
                "rate": "1.01111202",
                "rankrate": "1.01111202",
                "reserve": "1519450.843",
                "inmin": "1011.11212",
                "inmax": "30000",
                "marks": [
                    "floating",
                    "manual"
                ],
                "extra": []
            },
            {
                "changer": 1312,
                "rate": "1.009",
                "rankrate": "1.009",
                "reserve": "99000",
                "inmin": "1009",
                "inmax": "99891",
                "marks": [
                    "manual"
                ],
                "extra": []
            }
        ]
    }
}