{
    "rates": {
        "293-21": [
            {
                "changer": 455,
                "rate": "0.4857294627",
                "rankrate": "0.4857294627",
                "reserve": "58418.19",
                "inmin": "4500",
                "inmax": "20000",
                "marks": [
                    "cardverify",
                    "manual"
                ],
                "extra": []
            },
            {
                "changer": 1009,
                "rate": "0.5263157895",
                "rankrate": "0.5263157895",
                "reserve": "2532199.304",
                "inmin": "5000",
                "inmax": "27500",
                "marks": [
                    "cardverify",
                    "manual",
                    "reg"
                ],
                "extra": []
            },
            {
                "changer": 1065,
                "rate": "0.5007520294",
                "rankrate": "0.5007520294",
                "reserve": "1230366.995",
                "inmin": "6000",
                "inmax": "250000",
                "marks": [
                    "cardverify",
                    "manual"
                ],
                "extra": []
            }
        ]
    }
}