{
    "rates": {
        "48-227": [
            {
                "changer": 612,
                "rate": "1.470841342",
                "rankrate": "1.470841342",
                "reserve": "250159.1429",
                "inmin": "1365.70278",
                "inmax": "36412.21",
                "marks": [
                    "floating",
                    "verifying"
                ],
                "extra": []
            },
            {
                "changer": 1014,
                "rate": "1.466842995",
                "rankrate": "1.480141195",
                "reserve": "8585995.43",
                "inmin": "331.238965",
                "inmax": "10000000000",
                "marks": [
                    "floating",
                    "reg"
                ],
                "extra": {
                    "tofee": {
                        "value": "4.9",
                        "type": "absolute"
                    }
                }
            },
            {
                "changer": 1121,
                "rate": "1.478310209",
                "rankrate": "1.567393274",
                "reserve": "109321.2692",
                "inmin": "560",
                "inmax": "80805.37417",
                "marks": [
                    "floating"
                ],
                "extra": {
                    "tofee": {
                        "value": "30.75683068",
                        "type": "absolute"
                    }
                }
            },
            {
                "changer": 1156,
                "rate": "1.46403345",
                "rankrate": "1.46403345",
                "reserve": "440577.1178",
                "inmin": "21880.39844",
                "inmax": "2735049.869",
                "marks": [
                    "floating",
                    "manual"
                ],
                "extra": []
            },
            {
                "changer": 1161,
                "rate": "1.46047686",
                "rankrate": "1.46047686",
                "reserve": "1854979.401",
                "inmin": "27247.9564",
                "inmax": "27247956.4",
                "marks": [
                    "floating"
                ],
                "extra": []
            },
            {
                "changer": 1167,
                "rate": "1.461208203",
                "rankrate": "1.461208203",
                "reserve": "1354134.963",
                "inmin": "34059.9455",
                "inmax": "27247956.4",
                "marks": [
                    "floating"
                ],
                "extra": []
            },
            {
                "changer": 1263,
                "rate": "1.45974627",
                "rankrate": "1.45974627",
                "reserve": "1548097.515",
                "inmin": "19073.56948",
                "inmax": "27247956.4",
                "marks": [
                    "floating"
                ],
                "extra": []
            },
            {
                "changer": 1286,
                "rate": "1.460184549",
                "rankrate": "1.460184549",
                "reserve": "1688789.804",
                "inmin": "40871.9346",
                "inmax": "27247956.4",
                "marks": [
                    "floating"
                ],
                "extra": []
            },
            {
                "changer": 1291,
                "rate": "1.453580193",
                "rankrate": "1.467471929",
                "reserve": "1873009.927",
                "inmin": "160.42",
                "inmax": "2722570.1",
                "marks": [],
                "extra": {
                    "tofee": {
                        "value": "5.21",
                        "type": "absolute"
                    }
                }
            },
            {
                "changer": 1294,
                "rate": "1.461940278",
                "rankrate": "1.461940278",
                "reserve": "1855119.85",
                "inmin": "54495.91281",
                "inmax": "27247956.4",
                "marks": [
                    "floating"
                ],
                "extra": []
            },
            {
                "changer": 1319,
                "rate": "1.460769309",
                "rankrate": "1.460769309",
                "reserve": "1298583.895",
                "inmin": "41416.89373",
                "inmax": "27247956.4",
                "marks": [
                    "floating"
                ],
                "extra": []
            },
            {
                "changer": 1325,
                "rate": "1.457216917",
                "rankrate": "1.457216917",
                "reserve": "3740643.713",
                "inmin": "10068.46557",
                "inmax": "2239894.075",
                "marks": [
                    "floating"
                ],
                "extra": []
            }
        ]
    }
}